tplink_m7200/__init__.py
tplink_m7200/__main__.py
tplink_m7200/cli.py
tplink_m7200/client.py
tplink_m7200-20251222.dist-info/licenses/LICENSE
tplink_m7200-20251222.dist-info/METADATA
tplink_m7200-20251222.dist-info/WHEEL
tplink_m7200-20251222.dist-info/entry_points.txt
tplink_m7200-20251222.dist-info/top_level.txt
tplink_m7200-20251222.dist-info/RECORD
