Metadata-Version: 2.4
Name: tplink-m7200
Version: 20251222
Summary: TP-Link M7000/M7200 API client and CLI
Author: Gürkan Vural
License: MIT
Project-URL: Homepage, https://github.com/gurkein/tplink-m7200
Project-URL: Repository, https://github.com/gurkein/tplink-m7200
Classifier: Development Status :: 3 - Alpha
Classifier: Intended Audience :: Developers
Classifier: License :: OSI Approved :: MIT License
Classifier: Operating System :: OS Independent
Classifier: Programming Language :: Python :: 3 :: Only
Classifier: Programming Language :: Python :: 3.11
Classifier: Programming Language :: Python :: 3.12
Classifier: Programming Language :: Python :: 3.13
Classifier: Topic :: System :: Networking
Requires-Python: >=3.11
License-File: LICENSE
Requires-Dist: aiohttp<4.0,>=3.8
Requires-Dist: async-timeout<5.0,>=4.0
Requires-Dist: pycryptodomex>=3.20.0
Dynamic: license-file
